README.rst
setup.cfg
setup.py
lmfinstall/__init__.py
lmfinstall/common.py
lmfinstall/publishtool.py
lmfinstall.egg-info/PKG-INFO
lmfinstall.egg-info/SOURCES.txt
lmfinstall.egg-info/dependency_links.txt
lmfinstall.egg-info/requires.txt
lmfinstall.egg-info/top_level.txt
lmfinstall/airflow/__init__.py
lmfinstall/airflow/airflow103.py
lmfinstall/ambari/__init__.py
lmfinstall/ambari/core.py
lmfinstall/cdh/__init__.py
lmfinstall/cdh/core.py
lmfinstall/cdh/jar/mysql-connector-java-5.1.45-bin.jar
lmfinstall/cdh/jar/postgresql-42.2.1.jar
lmfinstall/fastdfs/__init__.py
lmfinstall/fastdfs/v1/__init__.py
lmfinstall/fastdfs/v1/core.py
lmfinstall/greenplum/__init__.py
lmfinstall/greenplum/core.py
lmfinstall/greenplum/scene.py
lmfinstall/greenplum/support.py
lmfinstall/greenplum/gpplpython/plpython3.so
lmfinstall/greenplum/gpplpython/plpython3u--1.0.sql
lmfinstall/greenplum/gpplpython/plpython3u--unpackaged--1.0.sql
lmfinstall/greenplum/gpplpython/plpython3u.control
lmfinstall/mysql/__init__.py
lmfinstall/mysql/core.py
lmfinstall/postgresql/__init__.py
lmfinstall/postgresql/postgresql1061.py
lmfinstall/postgresql/plpython/plpython34.so
lmfinstall/postgresql/plpython/plpython35.so
lmfinstall/postgresql/plpython/read.txt
lmfinstall/python/__init__.py
lmfinstall/python/python352.py
lmfinstall/v1/__init__.py
lmfinstall/v1/airflow103.py
lmfinstall/v1/common.py
lmfinstall/v1/hadoop.py
lmfinstall/v1/hdp.py
lmfinstall/v1/postgresql.py
lmfinstall/v1/python.py
lmfinstall/v1/hadoopconf/core-site.xml
lmfinstall/v1/hadoopconf/hdfs-site.xml
lmfinstall/v1/hadoopconf/mapred-site.xml
lmfinstall/v1/hadoopconf/slaves
lmfinstall/v1/hadoopconf/yarn-site.xml
lmfinstall/v1/hdprepo/ambari.repo
lmfinstall/v1/hdprepo/hdp.repo
lmfinstall/v1/plpython/plpython34.so
lmfinstall/v1/plpython/plpython35.so
lmfinstall/v1/plpython/read.txt
lmfinstall/v2/__init__.py
lmfinstall/v2/common.py
lmfinstall/v2/greenplum.py
lmfinstall/v2/greenplum6_rpm.py
lmfinstall/v2/hadoop273.py
lmfinstall/v2/hawq.py
lmfinstall/v2/postgresql.py
lmfinstall/v2/pxf.py
lmfinstall/v2/python.py
lmfinstall/v2/python352.py
lmfinstall/v2/python368.py
lmfinstall/v2/gpplpython/plpython3.so
